[{"id":"293","title":"Hindustan Unilever","description":"Swachh Bharat Sundar Bharat initiative by hindustan unilever ","date":"2024-03-15","time":"12:23","location":"race course vadodara","image":"image2.png"},{"id":"431","title":"Nexa","description":"Stylish Baleno Car by Maruti Suzuki .","date":"2024-03-08","time":"14:24","location":"Wakad , Pimpri Chinchwad","image":"Baleno.jpg"},{"id":"2394","title":"Adani","description":"Adani Growth with goodness.","date":"2024-02-28","time":"14:30","location":"Wakad , Pimpri Chinchwad","image":"image1.jpeg"},{"id":"8413","title":"Royal Enfield","description":"Royal Enfield's new Bullet Motorcycle.","date":"2024-03-14","time":"15:32","location":"Wakad , Pimpri Chinchwad","image":"image3.jpg"},{"id":"532","title":"baleno 2","description":"xyz","date":"2024-04-11","time":"14:04","location":"Wakad , Pimpri Chinchwad","image":"Baleno.jpg"}]